{
    "type": "FeatureCollection",
    "features": [
        {
            "type": "Feature",
            "properties": {},
            "geometry": {
                "coordinates": [
                    69.66577501081315,
                    39.85577492297293
                ],
                "type": "Point"
            }
        },
        {
            "type": "Feature",
            "properties": {},
            "geometry": {
                "coordinates": [
                    69.50085700444319,
                    39.869634942532
                ],
                "type": "Point"
            }
        },
        {
            "type": "Feature",
            "properties": {},
            "geometry": {
                "coordinates": [
                    69.6404956083762,
                    39.9287395659577
                ],
                "type": "Point"
            }
        },
        {
            "type": "Feature",
            "properties": {},
            "geometry": {
                "coordinates": [
                    69.76207749628395,
                    40.01545703698591
                ],
                "type": "Point"
            }
        },
        {
            "type": "Feature",
            "properties": {},
            "geometry": {
                "coordinates": [
                    69.95588624829585,
                    40.063381129470514
                ],
                "type": "Point"
            }
        },
        {
            "type": "Feature",
            "properties": {},
            "geometry": {
                "coordinates": [
                    69.90653122449234,
                    39.718872689522755
                ],
                "type": "Point"
            }
        },
        {
            "type": "Feature",
            "properties": {},
            "geometry": {
                "coordinates": [
                    69.77772665017304,
                    39.86039524056363
                ],
                "type": "Point"
            }
        },
        {
            "type": "Feature",
            "properties": {},
            "geometry": {
                "coordinates": [
                    69.65631464484284,
                    39.844098889017346
                ],
                "type": "Point"
            }
        },
        {
            "type": "Feature",
            "properties": {},
            "geometry": {
                "coordinates": [
                    69.67752278250978,
                    39.85508440661465
                ],
                "type": "Point"
            }
        },
        {
            "type": "Feature",
            "properties": {},
            "geometry": {
                "coordinates": [
                    69.66627991434859,
                    39.84527599284647
                ],
                "type": "Point"
            }
        },
        {
            "type": "Feature",
            "properties": {},
            "geometry": {
                "coordinates": [
                    69.69566468340452,
                    39.847433964120285
                ],
                "type": "Point"
            }
        },
        {
            "type": "Feature",
            "properties": {},
            "geometry": {
                "coordinates": [
                    69.72351633407612,
                    39.83840926935997
                ],
                "type": "Point"
            }
        },
        {
            "type": "Feature",
            "properties": {},
            "geometry": {
                "coordinates": [
                    69.88939185128348,
                    39.97234897980505
                ],
                "type": "Point"
            }
        },
        {
            "type": "Feature",
            "properties": {},
            "geometry": {
                "coordinates": [
                    69.918265580879,
                    40.002559805394384
                ],
                "type": "Point"
            }
        },
        {
            "type": "Feature",
            "properties": {},
            "geometry": {
                "coordinates": [
                    69.98061239522443,
                    39.997470580311216
                ],
                "type": "Point"
            }
        },
        {
            "type": "Feature",
            "properties": {},
            "geometry": {
                "coordinates": [
                    69.98802246784797,
                    39.978676309853824
                ],
                "type": "Point"
            }
        },
        {
            "type": "Feature",
            "properties": {},
            "geometry": {
                "coordinates": [
                    69.9683474485665,
                    39.973781119951525
                ],
                "type": "Point"
            }
        },
        {
            "type": "Feature",
            "properties": {},
            "geometry": {
                "coordinates": [
                    69.94765035036102,
                    39.96046442950558
                ],
                "type": "Point"
            }
        },
        {
            "type": "Feature",
            "properties": {},
            "geometry": {
                "coordinates": [
                    69.91315518668719,
                    39.95576380178841
                ],
                "type": "Point"
            }
        },
        {
            "type": "Feature",
            "properties": {},
            "geometry": {
                "coordinates": [
                    69.87073891135333,
                    39.95047520938823
                ],
                "type": "Point"
            }
        },
        {
            "type": "Feature",
            "properties": {},
            "geometry": {
                "coordinates": [
                    69.87891554274225,
                    39.99159792637829
                ],
                "type": "Point"
            }
        },
        {
            "type": "Feature",
            "properties": {},
            "geometry": {
                "coordinates": [
                    69.93078604812044,
                    39.988857181645216
                ],
                "type": "Point"
            }
        },
        {
            "type": "Feature",
            "properties": {},
            "geometry": {
                "coordinates": [
                    69.88964737144201,
                    40.00314699944431
                ],
                "type": "Point"
            }
        },
        {
            "type": "Feature",
            "properties": {},
            "geometry": {
                "coordinates": [
                    69.88709217413242,
                    40.0164553725929
                ],
                "type": "Point"
            }
        },
        {
            "type": "Feature",
            "properties": {},
            "geometry": {
                "coordinates": [
                    70.00812388839276,
                    40.05614173872982
                ],
                "type": "Point"
            }
        },
        {
            "type": "Feature",
            "properties": {},
            "geometry": {
                "coordinates": [
                    70.05940795812066,
                    40.03278435539923
                ],
                "type": "Point"
            }
        },
        {
            "type": "Feature",
            "properties": {},
            "geometry": {
                "coordinates": [
                    70.08342707938388,
                    39.994998038969186
                ],
                "type": "Point"
            }
        },
        {
            "type": "Feature",
            "properties": {},
            "geometry": {
                "coordinates": [
                    70.18080189532108,
                    39.99997111793118
                ],
                "type": "Point"
            }
        },
        {
            "type": "Feature",
            "properties": {},
            "geometry": {
                "coordinates": [
                    70.23468262680672,
                    40.02284261626693
                ],
                "type": "Point"
            }
        },
        {
            "type": "Feature",
            "properties": {},
            "geometry": {
                "coordinates": [
                    70.27817671125831,
                    40.05365729110292
                ],
                "type": "Point"
            }
        },
        {
            "type": "Feature",
            "properties": {},
            "geometry": {
                "coordinates": [
                    70.31258249544024,
                    40.00196024698832
                ],
                "type": "Point"
            }
        },
        {
            "type": "Feature",
            "properties": {},
            "geometry": {
                "coordinates": [
                    70.02397407968408,
                    39.85586481481738
                ],
                "type": "Point"
            }
        },
        {
            "type": "Feature",
            "properties": {},
            "geometry": {
                "coordinates": [
                    70.03130107546647,
                    39.82351554668546
                ],
                "type": "Point"
            }
        },
        {
            "type": "Feature",
            "properties": {},
            "geometry": {
                "coordinates": [
                    70.05511381176126,
                    39.84883366155506
                ],
                "type": "Point"
            }
        },
        {
            "type": "Feature",
            "properties": {},
            "geometry": {
                "coordinates": [
                    69.9800121049852,
                    39.864301248006626
                ],
                "type": "Point"
            }
        },
        {
            "type": "Feature",
            "properties": {},
            "geometry": {
                "coordinates": [
                    70.05145031387065,
                    39.78974354331589
                ],
                "type": "Point"
            }
        },
        {
            "type": "Feature",
            "properties": {},
            "geometry": {
                "coordinates": [
                    70.01847883284705,
                    39.75877130187854
                ],
                "type": "Point"
            }
        },
        {
            "type": "Feature",
            "properties": {},
            "geometry": {
                "coordinates": [
                    70.102739285077,
                    39.733420010338676
                ],
                "type": "Point"
            }
        },
        {
            "type": "Feature",
            "properties": {},
            "geometry": {
                "coordinates": [
                    70.23096171598246,
                    39.78129794333259
                ],
                "type": "Point"
            }
        },
        {
            "type": "Feature",
            "properties": {},
            "geometry": {
                "coordinates": [
                    70.28774593330081,
                    39.87414243527098
                ],
                "type": "Point"
            }
        },
        {
            "type": "Feature",
            "properties": {},
            "geometry": {
                "coordinates": [
                    70.293241180128,
                    39.90927803252745
                ],
                "type": "Point"
            }
        },
        {
            "type": "Feature",
            "properties": {},
            "geometry": {
                "coordinates": [
                    70.37383813679,
                    39.959841647521074
                ],
                "type": "Point"
            }
        },
        {
            "type": "Feature",
            "properties": {},
            "geometry": {
                "coordinates": [
                    70.37200641386676,
                    39.97107293514986
                ],
                "type": "Point"
            }
        },
        {
            "type": "Feature",
            "properties": {},
            "geometry": {
                "coordinates": [
                    70.43207754978707,
                    39.968265287807384
                ],
                "type": "Point"
            }
        },
        {
            "type": "Feature",
            "properties": {},
            "geometry": {
                "coordinates": [
                    70.4302458008417,
                    39.93035074819204
                ],
                "type": "Point"
            }
        },
        {
            "type": "Feature",
            "properties": {},
            "geometry": {
                "coordinates": [
                    70.40276956665522,
                    39.88257662400861
                ],
                "type": "Point"
            }
        },
        {
            "type": "Feature",
            "properties": {},
            "geometry": {
                "coordinates": [
                    70.30385512358436,
                    39.85305243563292
                ],
                "type": "Point"
            }
        },
        {
            "type": "Feature",
            "properties": {},
            "geometry": {
                "coordinates": [
                    70.44306804346232,
                    39.844614619585684
                ],
                "type": "Point"
            }
        },
        {
            "type": "Feature",
            "properties": {},
            "geometry": {
                "coordinates": [
                    70.35148059617387,
                    39.812260051188304
                ],
                "type": "Point"
            }
        },
        {
            "type": "Feature",
            "properties": {},
            "geometry": {
                "coordinates": [
                    70.35148059617387,
                    39.782705617022486
                ],
                "type": "Point"
            }
        },
        {
            "type": "Feature",
            "properties": {},
            "geometry": {
                "coordinates": [
                    70.3001916256926,
                    39.75313848368066
                ],
                "type": "Point"
            }
        },
        {
            "type": "Feature",
            "properties": {},
            "geometry": {
                "coordinates": [
                    70.25073440415773,
                    39.71933192724137
                ],
                "type": "Point"
            }
        },
        {
            "type": "Feature",
            "properties": {},
            "geometry": {
                "coordinates": [
                    70.15574750043243,
                    39.691578836638854
                ],
                "type": "Point"
            }
        },
        {
            "type": "Feature",
            "properties": {},
            "geometry": {
                "coordinates": [
                    70.13559826202831,
                    39.67607238896039
                ],
                "type": "Point"
            }
        },
        {
            "type": "Feature",
            "properties": {},
            "geometry": {
                "coordinates": [
                    70.16124274726954,
                    39.669022852575296
                ],
                "type": "Point"
            }
        },
        {
            "type": "Feature",
            "properties": {},
            "geometry": {
                "coordinates": [
                    70.21069996880433,
                    39.6718427534565
                ],
                "type": "Point"
            }
        },
        {
            "type": "Feature",
            "properties": {},
            "geometry": {
                "coordinates": [
                    70.25832544139388,
                    39.6464595020995
                ],
                "type": "Point"
            }
        },
        {
            "type": "Feature",
            "properties": {},
            "geometry": {
                "coordinates": [
                    70.38471611865126,
                    39.70003543128675
                ],
                "type": "Point"
            }
        },
        {
            "type": "Feature",
            "properties": {},
            "geometry": {
                "coordinates": [
                    70.50927504696222,
                    39.75920257948502
                ],
                "type": "Point"
            }
        },
        {
            "type": "Feature",
            "properties": {},
            "geometry": {
                "coordinates": [
                    70.51843379169097,
                    39.802840992815106
                ],
                "type": "Point"
            }
        },
        {
            "type": "Feature",
            "properties": {},
            "geometry": {
                "coordinates": [
                    70.83489026243754,
                    40.05366252203936
                ],
                "type": "Point"
            }
        },
        {
            "type": "Feature",
            "properties": {},
            "geometry": {
                "coordinates": [
                    70.83332721010319,
                    40.059644389651424
                ],
                "type": "Point"
            }
        },
        {
            "type": "Feature",
            "properties": {},
            "geometry": {
                "coordinates": [
                    70.82863805309609,
                    40.07220460240393
                ],
                "type": "Point"
            }
        },
        {
            "type": "Feature",
            "properties": {},
            "geometry": {
                "coordinates": [
                    70.84348704695176,
                    40.086556297742675
                ],
                "type": "Point"
            }
        },
        {
            "type": "Feature",
            "properties": {},
            "geometry": {
                "coordinates": [
                    70.86146214881276,
                    40.09612241254118
                ],
                "type": "Point"
            }
        },
        {
            "type": "Feature",
            "properties": {},
            "geometry": {
                "coordinates": [
                    70.86927741049246,
                    40.11525060837985
                ],
                "type": "Point"
            }
        },
        {
            "type": "Feature",
            "properties": {},
            "geometry": {
                "coordinates": [
                    70.8552099394694,
                    40.126007854821495
                ],
                "type": "Point"
            }
        },
        {
            "type": "Feature",
            "properties": {},
            "geometry": {
                "coordinates": [
                    70.79894005538279,
                    40.078184844395224
                ],
                "type": "Point"
            }
        },
        {
            "type": "Feature",
            "properties": {},
            "geometry": {
                "coordinates": [
                    70.8020661643327,
                    40.065027621545426
                ],
                "type": "Point"
            }
        },
        {
            "type": "Feature",
            "properties": {},
            "geometry": {
                "coordinates": [
                    70.85324796575668,
                    40.058062612042704
                ],
                "type": "Point"
            }
        },
        {
            "type": "Feature",
            "properties": {},
            "geometry": {
                "coordinates": [
                    70.82237151612512,
                    40.05433104547143
                ],
                "type": "Point"
            }
        },
        {
            "type": "Feature",
            "properties": {},
            "geometry": {
                "coordinates": [
                    70.86299842353489,
                    40.02695998081509
                ],
                "type": "Point"
            }
        },
        {
            "type": "Feature",
            "properties": {},
            "geometry": {
                "coordinates": [
                    70.84512258427355,
                    40.01949323815538
                ],
                "type": "Point"
            }
        },
        {
            "type": "Feature",
            "properties": {},
            "geometry": {
                "coordinates": [
                    70.89712502575841,
                    39.97965681082863
                ],
                "type": "Point"
            }
        },
        {
            "type": "Feature",
            "properties": {},
            "geometry": {
                "coordinates": [
                    70.89712502575841,
                    39.97592095429607
                ],
                "type": "Point"
            }
        },
        {
            "type": "Feature",
            "properties": {},
            "geometry": {
                "coordinates": [
                    70.92433505269511,
                    39.94421893267017
                ],
                "type": "Point"
            }
        },
        {
            "type": "Feature",
            "properties": {},
            "geometry": {
                "coordinates": [
                    70.93766598931006,
                    39.94567897816242
                ],
                "type": "Point"
            }
        },
        {
            "type": "Feature",
            "properties": {},
            "geometry": {
                "coordinates": [
                    70.93068311774985,
                    39.94113651208639
                ],
                "type": "Point"
            }
        },
        {
            "type": "Feature",
            "properties": {},
            "geometry": {
                "coordinates": [
                    70.93554996762589,
                    39.94259662335702
                ],
                "type": "Point"
            }
        },
        {
            "type": "Feature",
            "properties": {},
            "geometry": {
                "coordinates": [
                    71.05970976751021,
                    39.98267718739791
                ],
                "type": "Point"
            }
        },
        {
            "type": "Feature",
            "properties": {},
            "geometry": {
                "coordinates": [
                    71.07854236050667,
                    39.99597119181567
                ],
                "type": "Point"
            }
        },
        {
            "type": "Feature",
            "properties": {},
            "geometry": {
                "coordinates": [
                    71.07431031713614,
                    39.99824064131178
                ],
                "type": "Point"
            }
        },
        {
            "type": "Feature",
            "properties": {},
            "geometry": {
                "coordinates": [
                    71.29245124513176,
                    39.95046371125292
                ],
                "type": "Point"
            }
        },
        {
            "type": "Feature",
            "properties": {},
            "geometry": {
                "coordinates": [
                    71.33702640235265,
                    39.97708036554377
                ],
                "type": "Point"
            }
        },
        {
            "type": "Feature",
            "properties": {},
            "geometry": {
                "coordinates": [
                    71.36035061252741,
                    39.948874329498125
                ],
                "type": "Point"
            }
        },
        {
            "type": "Feature",
            "properties": {},
            "geometry": {
                "coordinates": [
                    71.41321883811,
                    39.98859779327944
                ],
                "type": "Point"
            }
        },
        {
            "type": "Feature",
            "properties": {},
            "geometry": {
                "coordinates": [
                    71.43084157468638,
                    40.01599352333031
                ],
                "type": "Point"
            }
        },
        {
            "type": "Feature",
            "properties": {},
            "geometry": {
                "coordinates": [
                    71.50496073146167,
                    40.01281777017155
                ],
                "type": "Point"
            }
        },
        {
            "type": "Feature",
            "properties": {},
            "geometry": {
                "coordinates": [
                    71.76245873267825,
                    40.02869017435779
                ],
                "type": "Point"
            }
        },
        {
            "type": "Feature",
            "properties": {},
            "geometry": {
                "coordinates": [
                    71.75719146519893,
                    40.086139986518816
                ],
                "type": "Point"
            }
        },
        {
            "type": "Feature",
            "properties": {},
            "geometry": {
                "coordinates": [
                    71.73875602902189,
                    40.11132199079529
                ],
                "type": "Point"
            }
        },
        {
            "type": "Feature",
            "properties": {},
            "geometry": {
                "coordinates": [
                    71.8804048243843,
                    40.15260030181986
                ],
                "type": "Point"
            }
        },
        {
            "type": "Feature",
            "properties": {},
            "geometry": {
                "coordinates": [
                    72.0542246511908,
                    40.14857425329981
                ],
                "type": "Point"
            }
        },
        {
            "type": "Feature",
            "properties": {},
            "geometry": {
                "coordinates": [
                    72.07792735484716,
                    40.119378264775065
                ],
                "type": "Point"
            }
        },
        {
            "type": "Feature",
            "properties": {},
            "geometry": {
                "coordinates": [
                    72.10031324163327,
                    40.09722121751838
                ],
                "type": "Point"
            }
        },
        {
            "type": "Feature",
            "properties": {},
            "geometry": {
                "coordinates": [
                    72.0384229153762,
                    40.18379408012672
                ],
                "type": "Point"
            }
        },
        {
            "type": "Feature",
            "properties": {},
            "geometry": {
                "coordinates": [
                    72.0897787732965,
                    40.2350816892621
                ],
                "type": "Point"
            }
        },
        {
            "type": "Feature",
            "properties": {},
            "geometry": {
                "coordinates": [
                    72.14640189869618,
                    40.263223087970374
                ],
                "type": "Point"
            }
        },
        {
            "type": "Feature",
            "properties": {},
            "geometry": {
                "coordinates": [
                    72.59881210060558,
                    40.269811980342666
                ],
                "type": "Point"
            }
        },
        {
            "type": "Feature",
            "properties": {},
            "geometry": {
                "coordinates": [
                    72.64158709001583,
                    40.27797091367111
                ],
                "type": "Point"
            }
        },
        {
            "type": "Feature",
            "properties": {},
            "geometry": {
                "coordinates": [
                    72.60594126550671,
                    40.26165206263957
                ],
                "type": "Point"
            }
        },
        {
            "type": "Feature",
            "properties": {},
            "geometry": {
                "coordinates": [
                    72.81625163010924,
                    40.5182163840887
                ],
                "type": "Point"
            }
        },
        {
            "type": "Feature",
            "properties": {},
            "geometry": {
                "coordinates": [
                    72.8109047564331,
                    40.541245672780605
                ],
                "type": "Point"
            }
        },
        {
            "type": "Feature",
            "properties": {},
            "geometry": {
                "coordinates": [
                    72.80853371554699,
                    40.51541187154467
                ],
                "type": "Point"
            }
        },
        {
            "type": "Feature",
            "properties": {},
            "geometry": {
                "coordinates": [
                    72.8142457899234,
                    40.50684369412514
                ],
                "type": "Point"
            }
        },
        {
            "type": "Feature",
            "properties": {},
            "geometry": {
                "coordinates": [
                    72.79201501397009,
                    40.508252236835574
                ],
                "type": "Point"
            }
        },
        {
            "type": "Feature",
            "properties": {},
            "geometry": {
                "coordinates": [
                    72.78645731998179,
                    40.5218666245309
                ],
                "type": "Point"
            }
        },
        {
            "type": "Feature",
            "properties": {},
            "geometry": {
                "coordinates": [
                    72.78105400638151,
                    40.53453960383089
                ],
                "type": "Point"
            }
        },
        {
            "type": "Feature",
            "properties": {},
            "geometry": {
                "coordinates": [
                    72.78306095143233,
                    40.54204838663091
                ],
                "type": "Point"
            }
        },
        {
            "type": "Feature",
            "properties": {},
            "geometry": {
                "coordinates": [
                    72.78753798270122,
                    40.548265960323846
                ],
                "type": "Point"
            }
        },
        {
            "type": "Feature",
            "properties": {},
            "geometry": {
                "coordinates": [
                    72.79710956679273,
                    40.553544579247216
                ],
                "type": "Point"
            }
        },
        {
            "type": "Feature",
            "properties": {},
            "geometry": {
                "coordinates": [
                    72.8103862802098,
                    40.56105123164954
                ],
                "type": "Point"
            }
        },
        {
            "type": "Feature",
            "properties": {},
            "geometry": {
                "coordinates": [
                    72.81841406041465,
                    40.555773204525536
                ],
                "type": "Point"
            }
        },
        {
            "type": "Feature",
            "properties": {},
            "geometry": {
                "coordinates": [
                    72.81764215847281,
                    40.53348361375416
                ],
                "type": "Point"
            }
        },
        {
            "type": "Feature",
            "properties": {},
            "geometry": {
                "coordinates": [
                    72.75774256759755,
                    40.518463286761346
                ],
                "type": "Point"
            }
        },
        {
            "type": "Feature",
            "properties": {},
            "geometry": {
                "coordinates": [
                    72.76654224974578,
                    40.5161160566044
                ],
                "type": "Point"
            }
        },
        {
            "type": "Feature",
            "properties": {},
            "geometry": {
                "coordinates": [
                    72.7704017594609,
                    40.50930862444321
                ],
                "type": "Point"
            }
        },
        {
            "type": "Feature",
            "properties": {},
            "geometry": {
                "coordinates": [
                    72.77117366140274,
                    40.50437867318806
                ],
                "type": "Point"
            }
        },
        {
            "type": "Feature",
            "properties": {},
            "geometry": {
                "coordinates": [
                    74.57846439338462,
                    42.86794613943562
                ],
                "type": "Point"
            }
        },
        {
            "type": "Feature",
            "properties": {},
            "geometry": {
                "coordinates": [
                    74.56531323624162,
                    42.862843037796296
                ],
                "type": "Point"
            }
        },
        {
            "type": "Feature",
            "properties": {},
            "geometry": {
                "coordinates": [
                    74.5658289678951,
                    42.85263556898926
                ],
                "type": "Point"
            }
        },
        {
            "type": "Feature",
            "properties": {},
            "geometry": {
                "coordinates": [
                    74.59935152531563,
                    42.84772025999001
                ],
                "type": "Point"
            }
        },
        {
            "type": "Feature",
            "properties": {},
            "geometry": {
                "coordinates": [
                    74.62436451046807,
                    42.84790931756899
                ],
                "type": "Point"
            }
        },
        {
            "type": "Feature",
            "properties": {},
            "geometry": {
                "coordinates": [
                    74.6439623138914,
                    42.85830659265113
                ],
                "type": "Point"
            }
        },
        {
            "type": "Feature",
            "properties": {},
            "geometry": {
                "coordinates": [
                    74.6800635295755,
                    42.86605615032016
                ],
                "type": "Point"
            }
        },
        {
            "type": "Feature",
            "properties": {},
            "geometry": {
                "coordinates": [
                    74.66433371417023,
                    42.88022965322966
                ],
                "type": "Point"
            }
        },
        {
            "type": "Feature",
            "properties": {},
            "geometry": {
                "coordinates": [
                    74.65685560520643,
                    42.89232180171038
                ],
                "type": "Point"
            }
        },
        {
            "type": "Feature",
            "properties": {},
            "geometry": {
                "coordinates": [
                    74.63596847327543,
                    42.90252270823379
                ],
                "type": "Point"
            }
        },
        {
            "type": "Feature",
            "properties": {},
            "geometry": {
                "coordinates": [
                    74.59290488027972,
                    42.9029004871785
                ],
                "type": "Point"
            }
        },
        {
            "type": "Feature",
            "properties": {},
            "geometry": {
                "coordinates": [
                    74.59470994106428,
                    42.92386358908118
                ],
                "type": "Point"
            }
        },
        {
            "type": "Feature",
            "properties": {},
            "geometry": {
                "coordinates": [
                    74.57794866235338,
                    42.916310139935405
                ],
                "type": "Point"
            }
        },
        {
            "type": "Feature",
            "properties": {},
            "geometry": {
                "coordinates": [
                    74.55938232285914,
                    42.906489271696756
                ],
                "type": "Point"
            }
        },
        {
            "type": "Feature",
            "properties": {},
            "geometry": {
                "coordinates": [
                    74.54107384919035,
                    42.89005470442419
                ],
                "type": "Point"
            }
        },
        {
            "type": "Feature",
            "properties": {},
            "geometry": {
                "coordinates": [
                    74.5307592161376,
                    42.883252912569304
                ],
                "type": "Point"
            }
        },
        {
            "type": "Feature",
            "properties": {},
            "geometry": {
                "coordinates": [
                    74.51992885143258,
                    42.867001151782375
                ],
                "type": "Point"
            }
        },
        {
            "type": "Feature",
            "properties": {},
            "geometry": {
                "coordinates": [
                    74.5586424185764,
                    42.84185919373613
                ],
                "type": "Point"
            }
        },
        {
            "type": "Feature",
            "properties": {},
            "geometry": {
                "coordinates": [
                    74.52924571437589,
                    42.85471501074494
                ],
                "type": "Point"
            }
        },
        {
            "type": "Feature",
            "properties": {},
            "geometry": {
                "coordinates": [
                    74.56328400344995,
                    42.83788847421957
                ],
                "type": "Point"
            }
        },
        {
            "type": "Feature",
            "properties": {},
            "geometry": {
                "coordinates": [
                    74.59113351269133,
                    42.84129196371387
                ],
                "type": "Point"
            }
        },
        {
            "type": "Feature",
            "properties": {},
            "geometry": {
                "coordinates": [
                    74.61795155862956,
                    42.83751029714756
                ],
                "type": "Point"
            }
        },
        {
            "type": "Feature",
            "properties": {},
            "geometry": {
                "coordinates": [
                    74.62903978915998,
                    42.83883390677303
                ],
                "type": "Point"
            }
        },
        {
            "type": "Feature",
            "properties": {},
            "geometry": {
                "coordinates": [
                    74.61898302193396,
                    42.87682831575253
                ],
                "type": "Point"
            }
        },
        {
            "type": "Feature",
            "properties": {},
            "geometry": {
                "coordinates": [
                    74.60325320652868,
                    42.88740965862388
                ],
                "type": "Point"
            }
        },
        {
            "type": "Feature",
            "properties": {},
            "geometry": {
                "coordinates": [
                    76.2831923304638,
                    41.91017527070858
                ],
                "type": "Point"
            }
        },
        {
            "type": "Feature",
            "properties": {},
            "geometry": {
                "coordinates": [
                    75.39453240754938,
                    41.25260233525606
                ],
                "type": "Point"
            }
        },
        {
            "type": "Feature",
            "properties": {},
            "geometry": {
                "coordinates": [
                    75.39453248506896,
                    41.40329007518389
                ],
                "type": "Point"
            }
        },
        {
            "type": "Feature",
            "properties": {},
            "geometry": {
                "coordinates": [
                    75.08875723857778,
                    41.532173535429735
                ],
                "type": "Point"
            }
        },
        {
            "type": "Feature",
            "properties": {},
            "geometry": {
                "coordinates": [
                    75.40446450965871,
                    41.303677518306216
                ],
                "type": "Point"
            }
        },
        {
            "type": "Feature",
            "properties": {},
            "geometry": {
                "coordinates": [
                    75.42358548529702,
                    41.27596945473252
                ],
                "type": "Point"
            }
        },
        {
            "type": "Feature",
            "properties": {},
            "geometry": {
                "coordinates": [
                    75.35393050261106,
                    41.26467761082495
                ],
                "type": "Point"
            }
        },
        {
            "type": "Feature",
            "properties": {},
            "geometry": {
                "coordinates": [
                    72.6355092178583,
                    42.23099103726179
                ],
                "type": "Point"
            }
        },
        {
            "type": "Feature",
            "properties": {},
            "geometry": {
                "coordinates": [
                    72.67642550161005,
                    42.24471341985662
                ],
                "type": "Point"
            }
        },
        {
            "type": "Feature",
            "properties": {},
            "geometry": {
                "coordinates": [
                    72.71244581978547,
                    42.23280359844455
                ],
                "type": "Point"
            }
        },
        {
            "type": "Feature",
            "properties": {},
            "geometry": {
                "coordinates": [
                    72.7267840046888,
                    42.2100133291423
                ],
                "type": "Point"
            }
        },
        {
            "type": "Feature",
            "properties": {},
            "geometry": {
                "coordinates": [
                    72.74287074872777,
                    42.18902865194664
                ],
                "type": "Point"
            }
        },
        {
            "type": "Feature",
            "properties": {},
            "geometry": {
                "coordinates": [
                    72.68551800911123,
                    42.185141835872145
                ],
                "type": "Point"
            }
        },
        {
            "type": "Feature",
            "properties": {},
            "geometry": {
                "coordinates": [
                    72.63900633612815,
                    42.197319727520096
                ],
                "type": "Point"
            }
        },
        {
            "type": "Feature",
            "properties": {},
            "geometry": {
                "coordinates": [
                    72.62187045660829,
                    42.21985559092036
                ],
                "type": "Point"
            }
        },
        {
            "type": "Feature",
            "properties": {},
            "geometry": {
                "coordinates": [
                    72.67677521343757,
                    42.218560644108805
                ],
                "type": "Point"
            }
        }
    ]
}